repoaudit/__init__.py
repoaudit/apt.py
repoaudit/utils.py
repoaudit/yum.py
repoaudit-0.2.1.dist-info/entry_points.txt
repoaudit-0.2.1.dist-info/WHEEL
repoaudit-0.2.1.dist-info/METADATA
repoaudit-0.2.1.dist-info/RECORD
