Metadata-Version: 2.1
Name: repoaudit
Version: 0.2.1
Summary: CLI to validate yum/apt repositories
Requires-Python: >=3.9,<4.0
Classifier: Programming Language :: Python :: 3
Classifier: Programming Language :: Python :: 3.10
Classifier: Programming Language :: Python :: 3.9
Requires-Dist: click (>=8.1.3,<9.0.0)
Requires-Dist: python-debian (>=0.1.44,<0.2.0)
Requires-Dist: python-gnupg (>=0.4.9,<0.5.0)
Requires-Dist: requests (>=2.28.1,<3.0.0)
